spork/__init__.py
spork/__main__.py
spork/cli.py
spork/compiler/__init__.py
spork/compiler/codegen.py
spork/compiler/loader.py
spork/compiler/macros.py
spork/compiler/reader.py
spork/compiler/reader_macros.py
spork/lsp/__init__.py
spork/lsp/protocol.py
spork/lsp/server.py
spork/project/__init__.py
spork/project/build.py
spork/project/config.py
spork/project/dist.py
spork/project/manager.py
spork/project/scaffold.py
spork/repl/__init__.py
spork/repl/backend.py
spork/repl/nrepl.py
spork/runtime/__init__.py
spork/runtime/core.py
spork/runtime/json.py
spork/runtime/ns.py
spork/runtime/pds.c
spork/runtime/pds.cp314t-win_arm64.pyd
spork/runtime/pds.pyi
spork/runtime/types.py
spork/runtime/utils.py
spork/std/__init__.py
spork/std/json.spork
spork/std/map.spork
spork/std/prelude.spork
spork/std/string.spork
spork_lang-0.2.1.dist-info/licenses/LICENSE
spork_lang-0.2.1.dist-info/METADATA
spork_lang-0.2.1.dist-info/WHEEL
spork_lang-0.2.1.dist-info/entry_points.txt
spork_lang-0.2.1.dist-info/top_level.txt
spork_lang-0.2.1.dist-info/RECORD
