Metadata-Version: 2.4
Name: spork-lang
Version: 0.2.1
Summary: A Lisp to Python transpiler with persistent data structures
Author-email: Grant Wade <grant@spork.sh>
License-Expression: MIT
Project-URL: Homepage, https://github.com/spork-it/spork-lang
Project-URL: Documentation, https://github.com/spork-it/spork-lang#readme
Project-URL: Repository, https://github.com/spork-it/spork-lang
Project-URL: Issues, https://github.com/spork-it/spork-lang/issues
Project-URL: Changelog, https://github.com/grant-wade/spork/releases
Keywords: lisp,clojure,transpiler,compiler,persistent-data-structures,functional-programming,repl
Classifier: Development Status :: 3 - Alpha
Classifier: Environment :: Console
Classifier: Intended Audience :: Developers
Classifier: Operating System :: OS Independent
Classifier: Programming Language :: Python :: 3
Classifier: Programming Language :: Python :: 3.10
Classifier: Programming Language :: Python :: 3.11
Classifier: Programming Language :: Python :: 3.12
Classifier: Programming Language :: Python :: 3.13
Classifier: Programming Language :: Python :: 3.14
Classifier: Programming Language :: Lisp
Classifier: Programming Language :: Python :: Implementation :: CPython
Classifier: Topic :: Software Development :: Compilers
Classifier: Topic :: Software Development :: Interpreters
Classifier: Topic :: Software Development :: Libraries
Requires-Python: >=3.10
License-File: LICENSE
Requires-Dist: build>=1
Requires-Dist: setuptools>=77
Requires-Dist: wheel
Provides-Extra: dev
Requires-Dist: build; extra == "dev"
Requires-Dist: twine; extra == "dev"
Requires-Dist: numpy; extra == "dev"
Dynamic: license-file
